dplab/__init__.py
dplab/_version.py
dplab/experiments.py
dplab/main.py
dplab/monitor.py
dplab/library_workload/__init__.py
dplab/library_workload/baseline.py
dplab/library_workload/chorus.py
dplab/library_workload/diffprivlib.py
dplab/library_workload/opendp.py
dplab/library_workload/pydp.py
dplab/library_workload/tmlt.py
dplab/library_workload/util.py
dplab-0.0.7.dist-info/METADATA
dplab-0.0.7.dist-info/WHEEL
dplab-0.0.7.dist-info/entry_points.txt
dplab-0.0.7.dist-info/top_level.txt
dplab-0.0.7.dist-info/RECORD
