Metadata-Version: 2.1
Name: dplab
Version: 0.0.7
Summary: DPLab: Benchmarking Differential Privacy Aggregation Operations
Author: littleRound
Author-email: xiaoyuanliu@berkeley.edu
Requires-Dist: psutil
Requires-Dist: numpy
Requires-Dist: tinydb
Requires-Dist: tqdm
Requires-Dist: scipy
Requires-Dist: jpype1
Requires-Dist: diffprivlib (==0.5.2)
Requires-Dist: python-dp (==1.1.1)
Requires-Dist: opendp (==0.6.1)
